[
  {
    "slug": "comment_created_life#34_MDEyOklzc3VlQ29tbWVudDgyNjA2Mzg1Mw==",
    "contributor": "aayushsaini",
    "activity_definition": "comment_created",
    "title": "Commented on #34",
    "occured_at": "2021-04-24T09:23:29.000Z",
    "link": "https://github.com/ohcnetwork/life/pull/34#issuecomment-826063853",
    "text": null,
    "points": null,
    "meta": {}
  },
  {
    "slug": "issue_opened_life#284",
    "contributor": "aayushsaini",
    "activity_definition": "issue_opened",
    "title": "Opened issue #284",
    "occured_at": "2021-05-06T15:16:15.000Z",
    "link": "https://github.com/ohcnetwork/life/issues/284",
    "text": "[Semantic Bug] State or District's page does not opens up from search bar on click",
    "points": null,
    "meta": {}
  },
  {
    "slug": "issue_closed_life#284",
    "contributor": "aayushsaini",
    "activity_definition": "issue_closed",
    "title": "Closed issue #284",
    "occured_at": "2021-05-07T05:37:04.000Z",
    "link": "https://github.com/ohcnetwork/life/issues/284",
    "text": "[Semantic Bug] State or District's page does not opens up from search bar on click",
    "points": null,
    "meta": {}
  },
  {
    "slug": "comment_created_life#284_MDEyOklzc3VlQ29tbWVudDgzNDA4MTMxNQ==",
    "contributor": "aayushsaini",
    "activity_definition": "comment_created",
    "title": "Commented on #284",
    "occured_at": "2021-05-07T05:37:04.000Z",
    "link": "https://github.com/ohcnetwork/life/issues/284#issuecomment-834081315",
    "text": null,
    "points": null,
    "meta": {}
  },
  {
    "slug": "comment_created_life#34_MDEyOklzc3VlQ29tbWVudDgyNTg5MzM5MQ==",
    "contributor": "aayushsaini",
    "activity_definition": "comment_created",
    "title": "Commented on #34",
    "occured_at": "2021-04-23T20:10:44.000Z",
    "link": "https://github.com/ohcnetwork/life/pull/34#issuecomment-825893391",
    "text": null,
    "points": null,
    "meta": {}
  },
  {
    "slug": "pr_opened_life#34",
    "contributor": "aayushsaini",
    "activity_definition": "pr_opened",
    "title": "Opened pull request #34",
    "occured_at": "2021-04-23T19:47:17.000Z",
    "link": "https://github.com/ohcnetwork/life/pull/34",
    "text": "Text Color Fix for State's districts list page",
    "points": null,
    "meta": {}
  },
  {
    "slug": "pr_merged_life#34",
    "contributor": "aayushsaini",
    "activity_definition": "pr_merged",
    "title": "Merged pull request #34",
    "occured_at": "2021-04-24T11:56:38.000Z",
    "link": "https://github.com/ohcnetwork/life/pull/34",
    "text": "Text Color Fix for State's districts list page",
    "points": null,
    "meta": {}
  },
  {
    "slug": "pr_opened_life#54",
    "contributor": "aayushsaini",
    "activity_definition": "pr_opened",
    "title": "Opened pull request #54",
    "occured_at": "2021-04-24T08:05:45.000Z",
    "link": "https://github.com/ohcnetwork/life/pull/54",
    "text": "Merge pull request #1 from coronasafe/main",
    "points": null,
    "meta": {}
  },
  {
    "slug": "comment_created_life#284_MDEyOklzc3VlQ29tbWVudDgzMzY5NjI5Mg==",
    "contributor": "aayushsaini",
    "activity_definition": "comment_created",
    "title": "Commented on #284",
    "occured_at": "2021-05-06T17:11:56.000Z",
    "link": "https://github.com/ohcnetwork/life/issues/284#issuecomment-833696292",
    "text": null,
    "points": null,
    "meta": {}
  }
]