[
  {
    "slug": "pr_merged_care_fe#20",
    "contributor": "akshaykumar-m-s",
    "activity_definition": "pr_merged",
    "title": "Merged pull request #20",
    "occured_at": "2020-03-23T09:49:43.000Z",
    "link": "https://github.com/ohcnetwork/care_fe/pull/20",
    "text": "Feature/onboard ambulance",
    "points": null,
    "meta": {}
  },
  {
    "slug": "issue_assigned_care_fe#12_akshaykumar-m-s",
    "contributor": "akshaykumar-m-s",
    "activity_definition": "issue_assigned",
    "title": "Issue #12 assigned",
    "occured_at": "2020-03-22T17:16:10.000Z",
    "link": "https://github.com/ohcnetwork/care_fe/issues/12",
    "text": "Add a form to onboard ambulance",
    "points": null,
    "meta": {}
  },
  {
    "slug": "pr_opened_care_fe#20",
    "contributor": "akshaykumar-m-s",
    "activity_definition": "pr_opened",
    "title": "Opened pull request #20",
    "occured_at": "2020-03-23T09:33:03.000Z",
    "link": "https://github.com/ohcnetwork/care_fe/pull/20",
    "text": "Feature/onboard ambulance",
    "points": null,
    "meta": {}
  }
]