[
  {
    "slug": "comment_created_teleicu_middleware#24_IC_kwDOGUPkaM54dkU9",
    "contributor": "aryanraj2713",
    "activity_definition": "comment_created",
    "title": "Commented on #24",
    "occured_at": "2024-03-26T17:12:10.000Z",
    "link": "https://github.com/ohcnetwork/teleicu_middleware/issues/24#issuecomment-2021016893",
    "text": null,
    "points": null,
    "meta": {}
  },
  {
    "slug": "comment_created_teleicu_middleware#120_IC_kwDOGUPkaM54BXD_",
    "contributor": "aryanraj2713",
    "activity_definition": "comment_created",
    "title": "Commented on #120",
    "occured_at": "2024-03-21T20:08:45.000Z",
    "link": "https://github.com/ohcnetwork/teleicu_middleware/issues/120#issuecomment-2013622527",
    "text": null,
    "points": null,
    "meta": {}
  }
]