[
  {
    "slug": "pr_opened_leaderboard#485",
    "contributor": "its-harshitgoel",
    "activity_definition": "pr_opened",
    "title": "Opened pull request #485",
    "occured_at": "2024-08-08T18:13:04.000Z",
    "link": "https://github.com/ohcnetwork/leaderboard/pull/485",
    "text": "Updated Twitter icon to X logo",
    "points": null,
    "meta": {}
  },
  {
    "slug": "comment_created_leaderboard#484_IC_kwDOHYGCwM6Hq-kX",
    "contributor": "its-harshitgoel",
    "activity_definition": "comment_created",
    "title": "Commented on #484",
    "occured_at": "2024-08-08T16:10:09.000Z",
    "link": "https://github.com/ohcnetwork/leaderboard/issues/484#issuecomment-2276190487",
    "text": null,
    "points": null,
    "meta": {}
  },
  {
    "slug": "pr_opened_leaderboard#486",
    "contributor": "its-harshitgoel",
    "activity_definition": "pr_opened",
    "title": "Opened pull request #486",
    "occured_at": "2024-08-09T02:49:21.000Z",
    "link": "https://github.com/ohcnetwork/leaderboard/pull/486",
    "text": "Updated Social Icons in Contributors Section",
    "points": null,
    "meta": {}
  },
  {
    "slug": "pr_merged_leaderboard#486",
    "contributor": "its-harshitgoel",
    "activity_definition": "pr_merged",
    "title": "Merged pull request #486",
    "occured_at": "2024-08-09T04:10:17.000Z",
    "link": "https://github.com/ohcnetwork/leaderboard/pull/486",
    "text": "Updated Social Icons in Contributors Section",
    "points": null,
    "meta": {}
  },
  {
    "slug": "issue_opened_leaderboard#484",
    "contributor": "its-harshitgoel",
    "activity_definition": "issue_opened",
    "title": "Opened issue #484",
    "occured_at": "2024-08-08T15:28:43.000Z",
    "link": "https://github.com/ohcnetwork/leaderboard/issues/484",
    "text": "Twitter Icon Incorrect on Contributor Profile",
    "points": null,
    "meta": {}
  },
  {
    "slug": "comment_created_leaderboard#484_IC_kwDOHYGCwM6HqrYy",
    "contributor": "its-harshitgoel",
    "activity_definition": "comment_created",
    "title": "Commented on #484",
    "occured_at": "2024-08-08T15:29:31.000Z",
    "link": "https://github.com/ohcnetwork/leaderboard/issues/484#issuecomment-2276111922",
    "text": null,
    "points": null,
    "meta": {}
  },
  {
    "slug": "issue_assigned_leaderboard#484_its-harshitgoel",
    "contributor": "its-harshitgoel",
    "activity_definition": "issue_assigned",
    "title": "Issue #484 assigned",
    "occured_at": "2024-08-08T16:24:46.000Z",
    "link": "https://github.com/ohcnetwork/leaderboard/issues/484",
    "text": "Twitter Icon Incorrect on Contributor Profile",
    "points": null,
    "meta": {}
  }
]