[
  {
    "slug": "issue_opened_care_fe#9033",
    "contributor": "love-to-code108",
    "activity_definition": "issue_opened",
    "title": "Opened issue #9033",
    "occured_at": "2024-11-06T13:17:05.000Z",
    "link": "https://github.com/ohcnetwork/care_fe/issues/9033",
    "text": "Adding comments in the code base .",
    "points": null,
    "meta": {}
  },
  {
    "slug": "comment_created_care_fe#9033_IC_kwDODtfaXs6Stmpj",
    "contributor": "love-to-code108",
    "activity_definition": "comment_created",
    "title": "Commented on #9033",
    "occured_at": "2024-11-07T00:59:40.000Z",
    "link": "https://github.com/ohcnetwork/care_fe/issues/9033#issuecomment-2461428323",
    "text": null,
    "points": null,
    "meta": {}
  },
  {
    "slug": "comment_created_care_fe#9033_IC_kwDODtfaXs6SqLEd",
    "contributor": "love-to-code108",
    "activity_definition": "comment_created",
    "title": "Commented on #9033",
    "occured_at": "2024-11-06T13:18:35.000Z",
    "link": "https://github.com/ohcnetwork/care_fe/issues/9033#issuecomment-2460528925",
    "text": null,
    "points": null,
    "meta": {}
  }
]