[
  {
    "slug": "issue_opened_care_fe#15025",
    "contributor": "R1sh0bh-1",
    "activity_definition": "issue_opened",
    "title": "Opened issue #15025",
    "occured_at": "2026-01-06T05:13:18.000Z",
    "link": "https://github.com/ohcnetwork/care_fe/issues/15025",
    "text": "[Accessibility] Implement ARIA attributes and keyboard navigation for Patient Registration Form",
    "points": null,
    "meta": {}
  },
  {
    "slug": "comment_created_care_fe#15025_IC_kwDODtfaXs7daHBW",
    "contributor": "R1sh0bh-1",
    "activity_definition": "comment_created",
    "title": "Commented on #15025",
    "occured_at": "2026-01-06T12:58:26.000Z",
    "link": "https://github.com/ohcnetwork/care_fe/issues/15025#issuecomment-3714609238",
    "text": null,
    "points": null,
    "meta": {}
  }
]