[
  {
    "slug": "comment_created_care#2301_IC_kwDODsgdF86dHvIZ",
    "contributor": "Ritesh051",
    "activity_definition": "comment_created",
    "title": "Commented on #2301",
    "occured_at": "2025-02-05T08:25:52.000Z",
    "link": "https://github.com/ohcnetwork/care/issues/2301#issuecomment-2636050969",
    "text": null,
    "points": null,
    "meta": {}
  },
  {
    "slug": "comment_created_care#2614_IC_kwDODsgdF86dHuc-",
    "contributor": "Ritesh051",
    "activity_definition": "comment_created",
    "title": "Commented on #2614",
    "occured_at": "2025-02-05T08:24:27.000Z",
    "link": "https://github.com/ohcnetwork/care/issues/2614#issuecomment-2636048190",
    "text": null,
    "points": null,
    "meta": {}
  }
]